{
  "meta": {
    "fetched_at": 1763924800
  },
  "mappings": [
    {
      "keyword": "middag:",
      "icon": "food",
      "replacement": "",
      "mode": "replace_icon",
      "color": "",
      "match_type": "contains",
      "size_px": 22
    },
    {
      "keyword": "leire",
      "icon": "palette",
      "replacement": "Amalie",
      "mode": "add_all",
      "color": "YELLOW",
      "match_type": "contains",
      "size_px": 22
    },
    {
      "keyword": "ferie:",
      "icon": "umbrella-beach",
      "replacement": "",
      "mode": "replace_icon",
      "color": "",
      "match_type": "contains",
      "size_px": 22
    },
    {
      "keyword": "husk:",
      "icon": "bell",
      "replacement": "",
      "mode": "replace_icon",
      "color": "",
      "match_type": "contains",
      "size_px": 22
    },
    {
      "keyword": "bursdag:",
      "icon": "cake",
      "replacement": "bursdag",
      "mode": "replace_all",
      "color": "",
      "match_type": "contains",
      "size_px": 22
    },
    {
      "keyword": "r.i.p:",
      "icon": "grave-stone",
      "replacement": "",
      "mode": "replace_icon",
      "color": "",
      "match_type": "contains",
      "size_px": 22
    },
    {
      "keyword": "g16 ik",
      "icon": "soccer",
      "replacement": "Peter",
      "mode": "replace_all",
      "color": "BLUE",
      "match_type": "contains",
      "size_px": 22
    },
    {
      "keyword": "oslo",
      "icon": "city",
      "replacement": "",
      "mode": "add_icon",
      "color": "",
      "match_type": "contains",
      "size_px": 22
    },
    {
      "keyword": "amalie",
      "icon": "",
      "replacement": "Amalie",
      "mode": "replace_text",
      "color": "YELLOW",
      "match_type": "contains",
      "size_px": 22
    },
    {
      "keyword": "sigrid",
      "icon": "",
      "replacement": "Sigrid",
      "mode": "replace_text",
      "color": "RED",
      "match_type": "contains",
      "size_px": 22
    },
    {
      "keyword": "peter",
      "icon": "",
      "replacement": "Peter",
      "mode": "replace_text",
      "color": "BLUE",
      "match_type": "contains",
      "size_px": 22
    },
    {
      "keyword": "ingun",
      "icon": "",
      "replacement": "Ingun",
      "mode": "replace_text",
      "color": "GREEN",
      "match_type": "contains",
      "size_px": 22
    },
    {
      "keyword": "christian",
      "icon": "",
      "replacement": "Christian",
      "mode": "replace_text",
      "color": "BLACK",
      "match_type": "contains",
      "size_px": 22
    },
    {
      "keyword": "G16",
      "icon": "soccer",
      "replacement": "Peter",
      "mode": "replace_all",
      "color": "BLUE",
      "match_type": "contains",
      "size_px": 22
    },
    {
      "keyword": "skole",
      "icon": "school",
      "replacement": "",
      "mode": "add_icon",
      "color": "",
      "match_type": "contains",
      "size_px": 22
    },
    {
      "keyword": "istrening",
      "icon": "skate",
      "replacement": "Amalie",
      "mode": "add_all",
      "color": "YELLOW",
      "match_type": "contains",
      "size_px": 22
    },
    {
      "keyword": "malakoff",
      "icon": "school",
      "replacement": "",
      "mode": "add_icon",
      "color": "",
      "match_type": "contains",
      "size_px": 22
    },
    {
      "keyword": "gym",
      "icon": "gymnastics",
      "replacement": "",
      "mode": "add_icon",
      "color": "",
      "match_type": "contains",
      "size_px": 22
    },
    {
      "keyword": "jul",
      "icon": "hexagram",
      "replacement": "",
      "mode": "add_icon",
      "color": "",
      "match_type": "contains",
      "size_px": 22
    },
    {
      "keyword": "samtale",
      "icon": "forum-outline",
      "replacement": "",
      "mode": "add_icon",
      "color": "",
      "match_type": "contains",
      "size_px": 22
    },
    {
      "keyword": "bupp",
      "icon": "forum-outline",
      "replacement": "",
      "mode": "add_icon",
      "color": "",
      "match_type": "contains",
      "size_px": 22
    },
    {
      "keyword": "japp",
      "icon": "dog",
      "replacement": "Japp",
      "mode": "add_all",
      "color": "GRAY",
      "match_type": "contains",
      "size_px": 22
    },
    {
      "keyword": "Movar:",
      "icon": "trash-2",
      "replacement": "",
      "mode": "replace_icon",
      "color": "",
      "match_type": "contains",
      "size_px": 22
    },
    {
      "keyword": "c:",
      "icon": "",
      "replacement": "Christian",
      "mode": "replace_text",
      "color": "BLACK",
      "match_type": "contains",
      "size_px": 22
    },
    {
      "keyword": "s:",
      "icon": "",
      "replacement": "Sigrid",
      "mode": "replace_text",
      "color": "RED",
      "match_type": "contains",
      "size_px": 22
    },
    {
      "keyword": "a:",
      "icon": "",
      "replacement": "Amalie",
      "mode": "replace_text",
      "color": "YELLOW",
      "match_type": "contains",
      "size_px": 22
    },
    {
      "keyword": "p:",
      "icon": "",
      "replacement": "Peter",
      "mode": "replace_text",
      "color": "BLUE",
      "match_type": "contains",
      "size_px": 22
    },
    {
      "keyword": "i:",
      "icon": "",
      "replacement": "Ingun",
      "mode": "replace_text",
      "color": "GREEN",
      "match_type": "contains",
      "size_px": 22
    },
    {
      "keyword": "planleggingsdag",
      "icon": "school",
      "replacement": "",
      "mode": "add_icon",
      "color": "",
      "match_type": "contains",
      "size_px": 22
    },
    {
      "keyword": "spillermøte",
      "icon": "soccer",
      "replacement": "Peter",
      "mode": "add_all",
      "color": "BLUE",
      "match_type": "contains",
      "size_px": 22
    },
    {
      "keyword": "Offentlig Fridag:",
      "icon": "umbrella-beach",
      "replacement": "",
      "mode": "replace_icon",
      "color": "",
      "match_type": "contains",
      "size_px": 22
    }
  ]
}